LICENSE
LICENSE.txt
README.md
pyproject.toml
setup.cfg
setup.py
src/py_read_env.egg-info/PKG-INFO
src/py_read_env.egg-info/SOURCES.txt
src/py_read_env.egg-info/dependency_links.txt
src/py_read_env.egg-info/requires.txt
src/py_read_env.egg-info/top_level.txt
src/readenv/__init__.py
src/readenv/main.py