Metadata-Version: 2.1
Name: py-read-env
Version: 0.1.6
Summary: py read env for cross OS environment include windows
Home-page: https://github.com/liuspatt/py-read-env
Author: liuspatt
Author-email: liuspatt@readenv.com
License: MIT
Keywords: env,python,windows,environment variables,deployments,settings,env,configurations,python
Platform: UNKNOWN
Classifier: Development Status :: 5 - Production/Stable
Classifier: Programming Language :: Python
Classifier: Programming Language :: Python :: 3
Classifier: Programming Language :: Python :: 3.5
Classifier: Programming Language :: Python :: 3.6
Classifier: Programming Language :: Python :: 3.7
Classifier: Programming Language :: Python :: 3.8
Classifier: Programming Language :: Python :: 3.9
Classifier: Programming Language :: Python :: 3.10
Classifier: Programming Language :: Python :: Implementation :: PyPy
Classifier: Intended Audience :: Developers
Classifier: Intended Audience :: System Administrators
Classifier: License :: OSI Approved :: BSD License
Classifier: Operating System :: OS Independent
Classifier: Topic :: System :: Systems Administration
Classifier: Topic :: Utilities
Classifier: Environment :: Web Environment
Requires-Python: >=3.5
License-File: LICENSE
License-File: LICENSE.txt
